configuror/__init__.py
configuror/exceptions.py
configuror/main.py
configuror/utils.py
configuror-0.3.0.dist-info/LICENSE
configuror-0.3.0.dist-info/METADATA
configuror-0.3.0.dist-info/WHEEL
configuror-0.3.0.dist-info/RECORD
