Metadata-Version: 2.1
Name: configuror
Version: 0.3.0
Summary: A configuration management toolkit
Home-page: https://configuror.readthedocs.io/en/stable
License: Apache-2.0
Keywords: configuration,yaml,toml,dotenv,ini
Author: lewoudar
Author-email: lewoudar@gmail.com
Requires-Python: >=3.8,<4.0
Classifier: Intended Audience :: Developers
Classifier: License :: OSI Approved :: Apache Software License
Classifier: Operating System :: OS Independent
Classifier: Programming Language :: Python :: 3
Classifier: Programming Language :: Python :: 3.8
Classifier: Programming Language :: Python :: 3.9
Classifier: Programming Language :: Python :: 3.10
Classifier: Programming Language :: Python :: 3.11
Classifier: Programming Language :: Python :: 3.12
Classifier: Topic :: Utilities
Requires-Dist: pyyaml (>=6.0.1,<7.0.0)
Requires-Dist: toml (>=0.10.0,<0.11.0)
Project-URL: Bug Tracker, https://github.com/lewoudar/configuror/issues
Project-URL: Documentation, https://configuror.readthedocs.io/en/stable/usage
Project-URL: Repository, https://github.com/lewoudar/configuror
